algpred2/blast_binaries/linux/blastp
algpred2/blast_binaries/mac/blastp
algpred2/blast_binaries/windows/blastp.exe
algpred2/blast_binaries/windows/blastp.exe.manifest
algpred2/blast_binaries/windows/vcomp100.dll
algpred2/blast_db/data.phr
algpred2/blast_db/data.pin
algpred2/blast_db/data.psq
algpred2/blast_db/pos_ige_motifs.txt
algpred2/model/rf_model
algpred2/progs/MERCI_motif_locator.pl
algpred2/python_scripts/__init__.py
algpred2/python_scripts/algpred2.py
algpred2-1.4.dist-info/LICENSE.txt
algpred2-1.4.dist-info/METADATA
algpred2-1.4.dist-info/WHEEL
algpred2-1.4.dist-info/entry_points.txt
algpred2-1.4.dist-info/top_level.txt
algpred2-1.4.dist-info/RECORD
