Metadata-Version: 2.1
Name: algpred2
Version: 1.4
Summary: A tool to predict allergenic proteins and mapping of IgE epitopes 
Home-page: https://github.com/raghavagps/algpred2
Requires-Python: >=3.6
License-File: LICENSE.txt
Requires-Dist: numpy
Requires-Dist: pandas
Requires-Dist: argparse
